fieldlinetracer/__init__.py
fieldlinetracer/cache.py
fieldlinetracer/client.py
fieldlinetracer/hint.py
fieldlinetracer/inputs.py
fieldlinetracer/mapping.py
fieldlinetracer/w7x.py
fieldlinetracer/w7x_archive.py
fzj_ipp_webservices-1.2.dist-info/METADATA
fzj_ipp_webservices-1.2.dist-info/WHEEL
fzj_ipp_webservices-1.2.dist-info/top_level.txt
fzj_ipp_webservices-1.2.dist-info/RECORD
